redis_mutator/__init__.py
redis_mutator/method_names.py
redis_mutator/mutate.py
redis_mutator/redis_mutator.py
redis_mutator-0.2.4.dist-info/METADATA
redis_mutator-0.2.4.dist-info/WHEEL
redis_mutator-0.2.4.dist-info/RECORD
